Lowpassfilter/filter.v
module convolution (
    input clk,              
    input rst,              
    input signed [15:0] x_in,           
    output reg signed [31:0] y_out ,
    output reg signed [31:0] y_out_t 
);

    parameter FILTER_LENGTH = 39; 

    reg signed [15:0] x_buffer [0:FILTER_LENGTH-1];
    reg signed [15:0] h_lut [0:FILTER_LENGTH-1];  
    reg signed [63:0] accumulator;
         
    integer i;

    initial begin // Updated LUT
        h_lut[0] = 16'h01B; 
        h_lut[1] = 16'h023;
        h_lut[2] = 16'h033; 
        h_lut[3] = 16'h04C;
        h_lut[4] = 16'h072; 
        h_lut[5] = 16'h0A4;
        h_lut[6] = 16'h0E5; 
        h_lut[7] = 16'h135;
        h_lut[8] = 16'h191; 
        h_lut[9] = 16'h1FA;
        h_lut[10] = 16'h26B; 
        h_lut[11] = 16'h2E1;
        h_lut[12] = 16'h359; 
        h_lut[13] = 16'h3CD;
        h_lut[14] = 16'h439; 
        h_lut[15] = 16'h499;
        h_lut[16] = 16'h4E9; 
        h_lut[17] = 16'h524;
        h_lut[18] = 16'h549; 
        h_lut[19] = 16'h555;
        h_lut[20] = 16'h549; 
        h_lut[21] = 16'h524; 
        h_lut[22] = 16'h4E9;
        h_lut[23] = 16'h499; 
        h_lut[24] = 16'h439;
        h_lut[25] = 16'h3CD; 
        h_lut[26] = 16'h359;
        h_lut[27] = 16'h2E1; 
        h_lut[28] = 16'h26B;
        h_lut[29] = 16'h1FA; 
        h_lut[30] = 16'h191;
        h_lut[31] = 16'h135; 
        h_lut[32] = 16'h0E5;
        h_lut[33] = 16'h0A4; 
        h_lut[34] = 16'h072;
        h_lut[35] = 16'h04C; 
        h_lut[36] = 16'h033;
        h_lut[37] = 16'h023;
        h_lut[38] = 16'h01B;
    end

    always @(posedge clk, posedge rst) begin
        if (rst == 1) begin
            y_out <= 0;
            for (i = 0; i < FILTER_LENGTH; i = i + 1) begin
                x_buffer[i] <= 0;
            end
        end else begin
            if (x_in != 16'hFFFF) begin
                for (i = FILTER_LENGTH-1; i > 0; i = i - 1) begin
                    x_buffer[i] <= x_buffer[i-1];
                end
                x_buffer[0] <= x_in; 
                if (x_buffer[0][15] == 1) begin
                	x_buffer[0] = ~x_buffer[0] + 1;
                end
                y_out_t <= x_buffer[0];
            end else begin
                for (i = FILTER_LENGTH-1; i > 0; i = i - 1) begin
                    x_buffer[i] <= x_buffer[i-1];
                end
                x_buffer[0] <= 16'h0000;       
            end      	

            accumulator = 0;
            for (i = 0; i < FILTER_LENGTH; i = i + 1) begin
                accumulator = accumulator + (x_buffer[i] * h_lut[i]);
            end

            y_out <= accumulator[31:0];
        end
    end

endmodule

Lowpassfilter/tb.v
`timescale 1ns / 1ps

module tb_convolution;

    parameter DATA_WIDTH = 16;
    parameter ACCUM_WIDTH = 32;

    reg clk;
    reg rst;
    reg signed [DATA_WIDTH-1:0] x_in;
    wire signed [ACCUM_WIDTH-1:0] y_out;
    wire signed [ACCUM_WIDTH-1:0] y_out_t;
    integer i;
    real sine_val;
        
    convolution uut (
        .clk(clk),
        .rst(rst),
        .x_in(x_in),
        .y_out(y_out),
        .y_out_t(y_out_t)
    );

    always #5 clk = ~clk;

    initial begin
        clk = 0;
        rst = 1;
        x_in = 0;

        #10 rst = 0;


        for (i = 0; i < 100; i = i + 1) begin
            sine_val = $sin(2 * 3.14159 * i / 20); 
            x_in = $rtoi(sine_val * 32767);        
            #10;
        end
        
        x_in = 16'hFFFF;

        #500 $finish;
    end

    initial begin
        $dumpfile("my_designf.vcd");
        $dumpvars(0, tb_convolution);
    end

endmodule

Lowpassfilter/my_designf.vcd
$date
	Wed Nov  6 00:17:32 2024
$end
$version
	Icarus Verilog
$end
$timescale
	1ps
$end
$scope module tb_convolution $end
$var wire 32 ! y_out_t [31:0] $end
$var wire 32 " y_out [31:0] $end
$var reg 1 # clk $end
$var reg 1 $ rst $end
$var reg 16 % x_in [15:0] $end
$var integer 32 & i [31:0] $end
$var real 1 ' sine_val $end
$scope module uut $end
$var wire 1 # clk $end
$var wire 1 $ rst $end
$var wire 16 ( x_in [15:0] $end
$var reg 64 ) accumulator [63:0] $end
$var reg 32 * y_out [31:0] $end
$var reg 32 + y_out_t [31:0] $end
$var integer 32 , i [31:0] $end
$upscope $end
$upscope $end
$enddefinitions $end
#0
$dumpvars
b100111 ,
bx +
b0 *
bx )
b0 (
r0 '
bx &
b0 %
1$
0#
b0 "
bx !
$end
#5000
b100111 ,
1#
#10000
0#
b0 &
0$
#15000
b0 !
b0 +
b0 )
b100111 ,
1#
#20000
0#
b10011110001101 %
b10011110001101 (
r0.3090167420035501 '
b1 &
#25000
b100111 ,
1#
#30000
0#
b100101100111011 %
b100101100111011 (
r0.5877848229325425 '
b10 &
#35000
b1000010101111011111 "
b1000010101111011111 *
b10011110001101 !
b10011110001101 +
b1000010101111011111 )
b100111 ,
1#
#40000
0#
b110011110001101 %
b110011110001101 (
r0.8090165264524072 '
b11 &
#45000
b11010101011110000000 "
b11010101011110000000 *
b100101100111011 !
b100101100111011 +
b11010101011110000000 )
b100111 ,
1#
#50000
0#
b111100110111011 %
b111100110111011 (
r0.9510561882928809 '
b100 &
#55000
b111010001011000000111 "
b111010001011000000111 *
b110011110001101 !
b110011110001101 +
b111010001011000000111 )
b100111 ,
1#
#60000
0#
b111111111111110 %
b111111111111110 (
r0.9999999999991198 '
b101 &
#65000
b1101011011100110011101 "
b1101011011100110011101 *
b111100110111011 !
b111100110111011 +
b1101011011100110011101 )
b100111 ,
1#
#70000
0#
b111100110111011 %
b111100110111011 (
r0.9510570082965535 '
b110 &
#75000
b10110101011011111000000 "
b10110101011011111000000 *
b111111111111110 !
b111111111111110 +
b10110101011011111000000 )
b100111 ,
1#
#80000
0#
b110011110001101 %
b110011110001101 (
r0.8090180861922142 '
b111 &
#85000
b100100000010101100101010 "
b100100000010101100101010 *
b111100110111011 !
b111100110111011 +
b100100000010101100101010 )
b100111 ,
1#
#90000
0#
b100101100111100 %
b100101100111100 (
r0.58778696973054 '
b1000 &
#95000
b110110101110001101000101 "
b110110101110001101000101 *
b110011110001101 !
b110011110001101 +
b110110101110001101000101 )
b100111 ,
1#
#100000
0#
b10011110001101 %
b10011110001101 (
r0.3090192657165443 '
b1001 &
#105000
b1001111111110101111010110 "
b1001111111110101111010110 *
b100101100111100 !
b100101100111100 +
b1001111111110101111010110 )
b100111 ,
1#
#110000
0#
b0 %
b0 (
r2.65358979335273e-06 '
b1010 &
#115000
b1110000111001011111001011 "
b1110000111001011111001011 *
b10011110001101 !
b10011110001101 +
b1110000111001011111001011 )
b100111 ,
1#
#120000
0#
b1101100001110011 %
b1101100001110011 (
r-0.30901421828838 '
b1011 &
#125000
b10011010010011110010101010 "
b10011010010011110010101010 *
b0 !
b0 +
b10011010010011110010101010 )
b100111 ,
1#
#130000
0#
b1011010011000101 %
b1011010011000101 (
r-0.5877826761304062 '
b1100 &
#135000
b11001110100111000010110011 "
b11001110100111000010110011 *
b10011110001101 !
b10011110001101 +
b11001110100111000010110011 )
b100111 ,
1#
#140000
0#
b1001100001110100 %
b1001100001110100 (
r-0.8090149667069033 '
b1101 &
#145000
b100001011001001110011101010 "
b100001011001001110011101010 *
b100101100111011 !
b100101100111011 +
b100001011001001110011101010 )
b100111 ,
1#
#150000
0#
b1000011001000101 %
b1000011001000101 (
r-0.9510553682825112 '
b1110 &
#155000
b101001110101001011011111001 "
b101001110101001011011111001 *
b110011110001100 !
b110011110001100 +
b101001110101001011011111001 )
b100111 ,
1#
#160000
0#
b1000000000000010 %
b1000000000000010 (
r-0.9999999999920782 '
b1111 &
#165000
b110010110111101110110100010 "
b110010110111101110110100010 *
b111100110111011 !
b111100110111011 +
b110010110111101110110100010 )
b100111 ,
1#
#170000
0#
b1000011001000101 %
b1000011001000101 (
r-0.9510578282935293 '
b10000 &
#175000
b111100001001100111100111101 "
b111100001001100111100111101 *
b111111111111110 !
b111111111111110 +
b111100001001100111100111101 )
b100111 ,
1#
#180000
0#
b1001100001110011 %
b1001100001110011 (
r-0.8090196459263242 '
b10001 &
#185000
b1000101001110011000000101110 "
b1000101001110011000000101110 *
b111100110111011 !
b111100110111011 +
b1000101001110011000000101110 )
b100111 ,
1#
#190000
0#
b1011010011000100 %
b1011010011000100 (
r-0.5877891165243982 '
b10010 &
#195000
b1001101100101110111110110100 "
b1001101100101110111110110100 *
b110011110001101 !
b110011110001101 +
b1001101100101110111110110100 )
b100111 ,
1#
#200000
0#
b1101100001110011 %
b1101100001110011 (
r-0.3090217894273625 '
b10011 &
#205000
b1010100101101111011000000001 "
b1010100101101111011000000001 *
b100101100111100 !
b100101100111100 +
b1010100101101111011000000001 )
b100111 ,
1#
#210000
0#
b0 %
b0 (
r-5.307179586686775e-06 '
b10100 &
#215000
b1011010000101010100001101110 "
b1011010000101010100001101110 *
b10011110001101 !
b10011110001101 +
b1011010000101010100001101110 )
b100111 ,
1#
#220000
0#
b10011110001101 %
b10011110001101 (
r0.309011694571034 '
b10101 &
#225000
b1011101001110001001101011001 "
b1011101001110001001101011001 *
b0 !
b0 +
b1011101001110001001101011001 )
b100111 ,
1#
#230000
0#
b100101100111011 %
b100101100111011 (
r0.5877805293241315 '
b10110 &
#235000
b1011110000001101111101010000 "
b1011110000001101111101010000 *
b10011110001101 !
b10011110001101 +
b1011110000001101111101010000 )
b100111 ,
1#
#240000
0#
b110011110001100 %
b110011110001100 (
r0.8090134069557036 '
b10111 &
#245000
b1011011111110111011011000010 "
b1011011111110111011011000010 *
b100101100111011 !
b100101100111011 +
b1011011111110111011011000010 )
b100111 ,
1#
#250000
0#
b111100110111011 %
b111100110111011 (
r0.951054548265445 '
b11000 &
#255000
b1010111000000010001100110111 "
b1010111000000010001100110111 *
b110011110001100 !
b110011110001100 +
b1010111000000010001100110111 )
b100111 ,
1#
#260000
0#
b111111111111110 %
b111111111111110 (
r0.9999999999779952 '
b11001 &
#265000
b1001111001100010000100101110 "
b1001111001100010000100101110 *
b111100110111011 !
b111100110111011 +
b1001111001100010000100101110 )
b100111 ,
1#
#270000
0#
b111100110111011 %
b111100110111011 (
r0.9510586482838083 '
b11010 &
#275000
b1000100110110001010001111000 "
b1000100110110001010001111000 *
b111111111111110 !
b111111111111110 +
b1000100110110001010001111000 )
b100111 ,
1#
#280000
0#
b110011110001101 %
b110011110001101 (
r0.8090212056547371 '
b11011 &
#285000
b111000011101011010101100001 "
b111000011101011010101100001 *
b111100110111011 !
b111100110111011 +
b111000011101011010101100001 )
b100111 ,
1#
#290000
0#
b100101100111100 %
b100101100111100 (
r0.5877912633141184 '
b11100 &
#295000
b101010101011110010001111111 "
b101010101011110010001111111 *
b110011110001101 !
b110011110001101 +
b101010101011110010001111111 )
b100111 ,
1#
#300000
0#
b10011110001101 %
b10011110001101 (
r0.3090243131360039 '
b11101 &
#305000
b11100010010011110111111110 "
b11100010010011110111111110 *
b100101100111100 !
b100101100111100 +
b11100010010011110111111110 )
b100111 ,
1#
#310000
0#
b0 %
b0 (
r7.960769380871628e-06 '
b11110 &
#315000
b1110000111001111000010010 "
b1110000111001111000010010 *
b10011110001101 !
b10011110001101 +
b1110000111001111000010010 )
b100111 ,
1#
#320000
0#
b1101100001110011 %
b1101100001110011 (
r-0.3090091708515129 '
b11111 &
#325000
b111111111011011010100 "
b111111111011011010100 *
b0 !
b0 +
b111111111011011010100 )
b100111 ,
1#
#330000
0#
b1011010011000101 %
b1011010011000101 (
r-0.5877783825137168 '
b100000 &
#335000
b11111110101111110111101100011111 "
b11111110101111110111101100011111 *
b10011110001101 !
b10011110001101 +
b1111111111111111111111111111111111111110101111110111101100011111 )
b100111 ,
1#
#340000
0#
b1001100001110100 %
b1001100001110100 (
r-0.8090118471988061 '
b100001 &
#345000
b11111101101011100001110101000111 "
b11111101101011100001110101000111 *
b100101100111011 !
b100101100111011 +
b1111111111111111111111111111111111111101101011100001110101000111 )
b100111 ,
1#
#350000
0#
b1000011001000101 %
b1000011001000101 (
r-0.9510537282416817 '
b100010 &
#355000
b11111100111110100100001101101000 "
b11111100111110100100001101101000 *
b110011110001100 !
b110011110001100 +
b1111111111111111111111111111111111111100111110100100001101101000 )
b100111 ,
1#
#360000
0#
b1000000000000010 %
b1000000000000010 (
r-0.9999999999568706 '
b100011 &
#365000
b11111100101010110111110110000110 "
b11111100101010110111110110000110 *
b111100110111011 !
b111100110111011 +
b1111111111111111111111111111111111111100101010110111110110000110 )
b100111 ,
1#
#370000
0#
b1000011001000101 %
b1000011001000101 (
r-0.9510594682673899 '
b100100 &
#375000
b11111100110000011100011110011111 "
b11111100110000011100011110011111 *
b111111111111110 !
b111111111111110 +
b1111111111111111111111111111111111111100110000011100011110011111 )
b100111 ,
1#
#380000
0#
b1001100001110011 %
b1001100001110011 (
r-0.8090227653774542 '
b100101 &
#385000
b11111101001101010001010010011011 "
b11111101001101010001010010011011 *
b111100110111011 !
b111100110111011 +
b1111111111111111111111111111111111111101001101010001010010011011 )
b100111 ,
1#
#390000
0#
b1011010011000100 %
b1011010011000100 (
r-0.5877934100996981 '
b100110 &
#395000
b11111101111101100011110111111010 "
b11111101111101100011110111111010 *
b110011110001101 !
b110011110001101 +
b1111111111111111111111111111111111111101111101100011110111111010 )
b100111 ,
1#
#400000
0#
b1101100001110011 %
b1101100001110011 (
r-0.3090268368424709 '
b100111 &
#405000
b11111110111011111110001001111111 "
b11111110111011111110001001111111 *
b100101100111100 !
b100101100111100 +
b1111111111111111111111111111111111111110111011111110001001111111 )
b100111 ,
1#
#410000
0#
b0 %
b0 (
r-1.061435917322407e-05 '
b101000 &
#415000
b10000101010111100010 "
b10000101010111100010 *
b10011110001101 !
b10011110001101 +
b10000101010111100010 )
b100111 ,
1#
#420000
0#
b10011110001101 %
b10011110001101 (
r0.3090066471298125 '
b101001 &
#425000
b1000111111111100010101101 "
b1000111111111100010101101 *
b0 !
b0 +
b1000111111111100010101101 )
b100111 ,
1#
#430000
0#
b100101100111011 %
b100101100111011 (
r0.5877762356991648 '
b101010 &
#435000
b10001000111100001011110011 "
b10001000111100001011110011 *
b10011110001101 !
b10011110001101 +
b10001000111100001011110011 )
b100111 ,
1#
#440000
0#
b110011110001100 %
b110011110001100 (
r0.8090102874362129 '
b101011 &
#445000
b10111100011110111011000001 "
b10111100011110111011000001 *
b100101100111011 !
b100101100111011 +
b10111100011110111011000001 )
b100111 ,
1#
#450000
0#
b111100110111011 %
b111100110111011 (
r0.9510529082112219 '
b101100 &
#455000
b11011101100100110110111101 "
b11011101100100110110111101 *
b110011110001100 !
b110011110001100 +
b11011101100100110110111101 )
b100111 ,
1#
#460000
0#
b111111111111110 %
b111111111111110 (
r0.9999999999287045 '
b101101 &
#465000
b11101000111110101011110001 "
b11101000111110101011110001 *
b111100110111011 !
b111100110111011 +
b11101000111110101011110001 )
b100111 ,
1#
#470000
0#
b111100110111011 %
b111100110111011 (
r0.9510602882442745 '
b101110 &
#475000
b11011101100100111100000100 "
b11011101100100111100000100 *
b111111111111110 !
b111111111111110 +
b11011101100100111100000100 )
b100111 ,
1#
#480000
0#
b110011110001101 %
b110011110001101 (
r0.8090243250944735 '
b101111 &
#485000
b10111100011111000100010110 "
b10111100011111000100010110 *
b111100110111011 !
b111100110111011 +
b10111100011111000100010110 )
b100111 ,
1#
#490000
0#
b100101100111100 %
b100101100111100 (
r0.5877955568811403 '
b110000 &
#495000
b10001000111100011000010101 "
b10001000111100011000010101 *
b110011110001101 !
b110011110001101 +
b10001000111100011000010101 )
b100111 ,
1#
#500000
0#
b10011110001101 %
b10011110001101 (
r0.3090293605467619 '
b110001 &
#505000
b1000111111111110001110101 "
b1000111111111110001110101 *
b100101100111100 !
b100101100111100 +
b1000111111111110001110101 )
b100111 ,
1#
#510000
0#
b0 %
b0 (
r1.326794896550177e-05 '
b110010 &
#515000
b1000001111 "
b1000001111 *
b10011110001101 !
b10011110001101 +
b1000001111 )
b100111 ,
1#
#520000
0#
b1101100001110011 %
b1101100001110011 (
r-0.3090041234059412 '
b110011 &
#525000
b11111110111000000000011101110110 "
b11111110111000000000011101110110 *
b0 !
b0 +
b1111111111111111111111111111111111111110111000000000011101110110 )
b100111 ,
1#
#530000
0#
b1011010011000101 %
b1011010011000101 (
r-0.587774088880471 '
b110100 &
#535000
b11111101111001001001010011100110 "
b11111101111001001001010011100110 *
b10011110001101 !
b10011110001101 +
b1111111111111111111111111111111111111101111001001001010011100110 )
b100111 ,
1#
#540000
0#
b1001100001110100 %
b1001100001110100 (
r-0.8090087276679232 '
b110101 &
#545000
b11111101000111011110111110110001 "
b11111101000111011110111110110001 *
b100101100111011 !
b100101100111011 +
b1111111111111111111111111111111111111101000111011110111110110001 )
b100111 ,
1#
#550000
0#
b1000011001000101 %
b1000011001000101 (
r-0.9510520881740652 '
b110110 &
#555000
b11111100100111111000100111001011 "
b11111100100111111000100111001011 *
b110011110001100 !
b110011110001100 +
b1111111111111111111111111111111111111100100111111000100111001011 )
b100111 ,
1#
#560000
0#
b1000000000000010 %
b1000000000000010 (
r-0.9999999998934967 '
b110111 &
#565000
b11111100011101011100001010000001 "
b11111100011101011100001010000001 *
b111100110111011 !
b111100110111011 +
b1111111111111111111111111111111111111100011101011100001010000001 )
b100111 ,
1#
#570000
0#
b1000011001000101 %
b1000011001000101 (
r-0.9510611082144632 '
b111000 &
#575000
b11111100101001001011000010010000 "
b11111100101001001011000010010000 *
b111111111111110 !
b111111111111110 +
b1111111111111111111111111111111111111100101001001011000010010000 )
b100111 ,
1#
#580000
0#
b1001100001110011 %
b1001100001110011 (
r-0.8090258848057961 '
b111001 &
#585000
b11111101001001111011110001011100 "
b11111101001001111011110001011100 *
b111100110111011 !
b111100110111011 +
b1111111111111111111111111111111111111101001001111011110001011100 )
b100111 ,
1#
#590000
0#
b1011010011000100 %
b1011010011000100 (
r-0.5877977036584406 '
b111010 &
#595000
b11111101111100100001000110101001 "
b11111101111100100001000110101001 *
b110011110001101 !
b110011110001101 +
b1111111111111111111111111111111111111101111100100001000110101001 )
b100111 ,
1#
#600000
0#
b1101100001110010 %
b1101100001110010 (
r-0.3090318842488769 '
b111011 &
#605000
b11111110111011111110001000110011 "
b11111110111011111110001000110011 *
b100101100111100 !
b100101100111100 +
b1111111111111111111111111111111111111110111011111110001000110011 )
b100111 ,
1#
#610000
0#
b0 %
b0 (
r-1.592153876123875e-05 '
b111100 &
#615000
b10000101010111001010 "
b10000101010111001010 *
b10011110001110 !
b10011110001110 +
b10000101010111001010 )
b100111 ,
1#
#620000
0#
b10011110001101 %
b10011110001101 (
r0.3090015996798925 '
b111101 &
#625000
b1000111111111100001100111 "
b1000111111111100001100111 *
b0 !
b0 +
b1000111111111100001100111 )
b100111 ,
1#
#630000
0#
b100101100111011 %
b100101100111011 (
r0.587771942057644 '
b111110 &
#635000
b10001000111100001010100101 "
b10001000111100001010100101 *
b10011110001101 !
b10011110001101 +
b10001000111100001010100101 )
b100111 ,
1#
#640000
0#
b110011110001100 %
b110011110001100 (
r0.8090071678939347 '
b111111 &
#645000
b10111100011110111001110101 "
b10111100011110111001110101 *
b100101100111011 !
b100101100111011 +
b10111100011110111001110101 )
b100111 ,
1#
#650000
0#
b111100110111011 %
b111100110111011 (
r0.9510512681302105 '
b1000000 &
#655000
b11011101100100110101001011 "
b11011101100100110101001011 *
b110011110001100 !
b110011110001100 +
b11011101100100110101001011 )
b100111 ,
1#
#660000
0#
b111111111111110 %
b111111111111110 (
r0.9999999998512475 '
b1000001 &
#665000
b11101000111110101001001101 "
b11101000111110101001001101 *
b111100110111011 !
b111100110111011 +
b11101000111110101001001101 )
b100111 ,
1#
#670000
0#
b111100110111011 %
b111100110111011 (
r0.951061928177954 '
b1000010 &
#675000
b11011101100100111000011111 "
b11011101100100111000011111 *
b111111111111110 !
b111111111111110 +
b11011101100100111000011111 )
b100111 ,
1#
#680000
0#
b110011110001101 %
b110011110001101 (
r0.8090274445114239 '
b1000011 &
#685000
b10111100011110111111100001 "
b10111100011110111111100001 *
b111100110111011 !
b111100110111011 +
b10111100011110111111100001 )
b100111 ,
1#
#690000
0#
b100101100111100 %
b100101100111100 (
r0.5877998504316062 '
b1000100 &
#695000
b10001000111100010010000100 "
b10001000111100010010000100 *
b110011110001101 !
b110011110001101 +
b10001000111100010010000100 )
b100111 ,
1#
#700000
0#
b10011110001110 %
b10011110001110 (
r0.3090344079488108 '
b1000101 &
#705000
b1000111111111101001111011 "
b1000111111111101001111011 *
b100101100111100 !
b100101100111100 +
b1000111111111101001111011 )
b100111 ,
1#
#710000
0#
b0 %
b0 (
r1.857512855331091e-05 '
b1000110 &
#715000
b11111111111111111111111110111111 "
b11111111111111111111111110111111 *
b10011110001110 !
b10011110001110 +
b1111111111111111111111111111111111111111111111111111111110111111 )
b100111 ,
1#
#720000
0#
b1101100001110100 %
b1101100001110100 (
r-0.3089990759516645 '
b1000111 &
#725000
b11111110111000000000010010111000 "
b11111110111000000000010010111000 *
b0 !
b0 +
b1111111111111111111111111111111111111110111000000000010010111000 )
b100111 ,
1#
#730000
0#
b1011010011000101 %
b1011010011000101 (
r-0.5877697952306726 '
b1001000 &
#735000
b11111101111001001001000110100101 "
b11111101111001001001000110100101 *
b10011110001100 !
b10011110001100 +
b1111111111111111111111111111111111111101111001001001000110100101 )
b100111 ,
1#
#740000
0#
b1001100001110100 %
b1001100001110100 (
r-0.8090056081142515 '
b1001001 &
#745000
b11111101000111011110110001010011 "
b11111101000111011110110001010011 *
b100101100111011 !
b100101100111011 +
b1111111111111111111111111111111111111101000111011110110001010011 )
b100111 ,
1#
#750000
0#
b1000011001000101 %
b1000011001000101 (
r-0.95105044807966 '
b1001010 &
#755000
b11111100100111111000011000110111 "
b11111100100111111000011000110111 *
b110011110001100 !
b110011110001100 +
b1111111111111111111111111111111111111100100111111000011000110111 )
b100111 ,
1#
#760000
0#
b1000000000000010 %
b1000000000000010 (
r-0.9999999998019568 '
b1001011 &
#765000
b11111100011101011011111011011000 "
b11111100011101011011111011011000 *
b111100110111011 !
b111100110111011 +
b1111111111111111111111111111111111111100011101011011111011011000 )
b100111 ,
1#
#770000
0#
b1000011001000101 %
b1000011001000101 (
r-0.9510627481347478 '
b1001100 &
#775000
b11111100101001001010110011111110 "
b11111100101001001010110011111110 *
b111111111111110 !
b111111111111110 +
b1111111111111111111111111111111111111100101001001010110011111110 )
b100111 ,
1#
#780000
0#
b1001100001110011 %
b1001100001110011 (
r-0.8090290042113528 '
b1001101 &
#785000
b11111101001001111011100100010001 "
b11111101001001111011100100010001 *
b111100110111011 !
b111100110111011 +
b1111111111111111111111111111111111111101001001111011100100010001 )
b100111 ,
1#
#790000
0#
b1011010011000100 %
b1011010011000100 (
r-0.58780199720063 '
b1001110 &
#795000
b11111101111100100000111011010110 "
b11111101111100100000111011010110 *
b110011110001101 !
b110011110001101 +
b1111111111111111111111111111111111111101111100100000111011010110 )
b100111 ,
1#
#800000
0#
b1101100001110010 %
b1101100001110010 (
r-0.3090369316465753 '
b1001111 &
#805000
b11111110111011111110000000001101 "
b11111110111011111110000000001101 *
b100101100111100 !
b100101100111100 +
b1111111111111111111111111111111111111110111011111110000000001101 )
b100111 ,
1#
#810000
0#
b0 %
b0 (
r-2.122871834525227e-05 '
b1010000 &
#815000
b10000101010001111101 "
b10000101010001111101 *
b10011110001110 !
b10011110001110 +
b10000101010001111101 )
b100111 ,
1#
#820000
0#
b10011110001100 %
b10011110001100 (
r0.308996552221264 '
b1010001 &
#825000
b1000111111111100000011110 "
b1000111111111100000011110 *
b0 !
b0 +
b1000111111111100000011110 )
b100111 ,
1#
#830000
0#
b100101100111011 %
b100101100111011 (
r0.5877676483995624 '
b1010010 &
#835000
b10001000111100001101100101 "
b10001000111100001101100101 *
b10011110001100 !
b10011110001100 +
b10001000111100001101100101 )
b100111 ,
1#
#840000
0#
b110011110001100 %
b110011110001100 (
r0.8090040483288696 '
b1010011 &
#845000
b10111100011111000001100111 "
b10111100011111000001100111 *
b100101100111011 !
b100101100111011 +
b10111100011111000001100111 )
b100111 ,
1#
#850000
0#
b111100110111011 %
b111100110111011 (
r0.9510496280224127 '
b1010100 &
#855000
b11011101100101000001110001 "
b11011101100101000001110001 *
b110011110001100 !
b110011110001100 +
b11011101100101000001110001 )
b100111 ,
1#
#860000
0#
b111111111111110 %
b111111111111110 (
r0.9999999997456244 '
b1010101 &
#865000
b11101000111110111010011010 "
b11101000111110111010011010 *
b111100110111011 !
b111100110111011 +
b11101000111110111010011010 )
b100111 ,
1#
#870000
0#
b111100110111011 %
b111100110111011 (
r0.9510635680848447 '
b1010110 &
#875000
b11011101100101001101110110 "
b11011101100101001101110110 *
b111111111111110 !
b111111111111110 +
b11011101100101001101110110 )
b100111 ,
1#
#880000
0#
b110011110001101 %
b110011110001101 (
r0.809030563905585 '
b1010111 &
#885000
b10111100011111011000011001 "
b10111100011111011000011001 *
b111100110111011 !
b111100110111011 +
b10111100011111011000011001 )
b100111 ,
1#
#890000
0#
b100101100111100 %
b100101100111100 (
r0.5878041439655147 '
b1011000 &
#895000
b10001000111100101101100110 "
b10001000111100101101100110 *
b110011110001101 !
b110011110001101 +
b10001000111100101101100110 )
b100111 ,
1#
#900000
0#
b10011110001110 %
b10011110001110 (
r0.3090394553421637 '
b1011001 &
#905000
b1001000000000000111000101 "
b1001000000000000111000101 *
b100101100111100 !
b100101100111100 +
b1001000000000000111000101 )
b100111 ,
1#
#910000
0#
b0 %
b0 (
r2.388230814059686e-05 '
b1011010 &
#915000
b11100101111 "
b11100101111 *
b10011110001110 !
b10011110001110 +
b11100101111 )
b100111 ,
1#
#920000
0#
b1101100001110100 %
b1101100001110100 (
r-0.3089940284886844 '
b1011011 &
#925000
b11111110111000000000110000000010 "
b11111110111000000000110000000010 *
b0 !
b0 +
b1111111111111111111111111111111111111110111000000000110000000010 )
b100111 ,
1#
#930000
0#
b1011010011000101 %
b1011010011000101 (
r-0.5877655015643191 '
b1011100 &
#935000
b11111101111001001001100010000111 "
b11111101111001001001100010000111 *
b10011110001100 !
b10011110001100 +
b1111111111111111111111111111111111111101111001001001100010000111 )
b100111 ,
1#
#940000
0#
b1001100001110100 %
b1001100001110100 (
r-0.8090024885377953 '
b1011101 &
#945000
b11111101000111011111001010001011 "
b11111101000111011111001010001011 *
b100101100111011 !
b100101100111011 +
b1111111111111111111111111111111111111101000111011111001010001011 )
b100111 ,
1#
#950000
0#
b1000011001000101 %
b1000011001000101 (
r-0.9510488079584686 '
b1011110 &
#955000
b11111100100111111000101110001110 "
b11111100100111111000101110001110 *
b110011110001100 !
b110011110001100 +
b1111111111111111111111111111111111111100100111111000101110001110 )
b100111 ,
1#
#960000
0#
b1000000000000010 %
b1000000000000010 (
r-0.9999999996822505 '
b1011111 &
#965000
b11111100011101011100001100100101 "
b11111100011101011100001100100101 *
b111100110111011 !
b111100110111011 +
b1111111111111111111111111111111111111100011101011100001100100101 )
b100111 ,
1#
#970000
0#
b1000011001000101 %
b1000011001000101 (
r-0.9510643880282458 '
b1100000 &
#975000
b11111100101001001011000000100100 "
b11111100101001001011000000100100 *
b111111111111110 !
b111111111111110 +
b1111111111111111111111111111111111111100101001001011000000100100 )
b100111 ,
1#
#980000
0#
b1001100001110011 %
b1001100001110011 (
r-0.8090321235941224 '
b1100001 &
#985000
b11111101001001111011101100000011 "
b11111101001001111011101100000011 *
b111100110111011 !
b111100110111011 +
b1111111111111111111111111111111111111101001001111011101100000011 )
b100111 ,
1#
#990000
0#
b1011010011000100 %
b1011010011000100 (
r-0.5878062907262632 '
b1100010 &
#995000
b11111101111100100000111110010110 "
b11111101111100100000111110010110 *
b110011110001101 !
b110011110001101 +
b1111111111111111111111111111111111111101111100100000111110010110 )
b100111 ,
1#
#1000000
0#
b1101100001110010 %
b1101100001110010 (
r-0.3090419790355726 '
b1100011 &
#1005000
b11111110111011111101111111000100 "
b11111110111011111101111111000100 *
b100101100111100 !
b100101100111100 +
b1111111111111111111111111111111111111110111011111101111111000100 )
b100111 ,
1#
#1010000
0#
b1111111111111111 %
b1111111111111111 (
b1100100 &
#1015000
b11111111111111111111101100111100 "
b11111111111111111111101100111100 *
b1111111111111111111111111111111111111111111111111111101100111100 )
b100111 ,
1#
#1020000
0#
#1025000
b1000111111111010111111000 "
b1000111111111010111111000 *
b1000111111111010111111000 )
b100111 ,
1#
#1030000
0#
#1035000
b10000111111001010011001110 "
b10000111111001010011001110 *
b10000111111001010011001110 )
b100111 ,
1#
#1040000
0#
#1045000
b10111001001001010110111111 "
b10111001001001010110111111 *
b10111001001001010110111111 )
b100111 ,
1#
#1050000
0#
#1055000
b11010110010011011100100110 "
b11010110010011011100100110 *
b11010110010011011100100110 )
b100111 ,
1#
#1060000
0#
#1065000
b11011011100011000111000011 "
b11011011100011000111000011 *
b11011011100011000111000011 )
b100111 ,
1#
#1070000
0#
#1075000
b11000110111001100011000111 "
b11000110111001100011000111 *
b11000110111001100011000111 )
b100111 ,
1#
#1080000
0#
#1085000
b10011000011100100010000001 "
b10011000011100100010000001 *
b10011000011100100010000001 )
b100111 ,
1#
#1090000
0#
#1095000
b1010010001110011001101101 "
b1010010001110011001101101 *
b1010010001110011001101101 )
b100111 ,
1#
#1100000
0#
#1105000
b11111111111000000001010100001010 "
b11111111111000000001010100001010 *
b1111111111111111111111111111111111111111111000000001010100001010 )
b100111 ,
1#
#1110000
0#
#1115000
b11111110001111000110111101101111 "
b11111110001111000110111101101111 *
b1111111111111111111111111111111111111110001111000110111101101111 )
b100111 ,
1#
#1120000
0#
#1125000
b11111100011101101101000001101010 "
b11111100011101101101000001101010 *
b1111111111111111111111111111111111111100011101101101000001101010 )
b100111 ,
1#
#1130000
0#
